README
setup.py
django_htauth.egg-info/PKG-INFO
django_htauth.egg-info/SOURCES.txt
django_htauth.egg-info/dependency_links.txt
django_htauth.egg-info/entry_points.txt
django_htauth.egg-info/not-zip-safe
django_htauth.egg-info/top_level.txt
htauth/__init__.py
htauth/backend.py
htauth/htpasswd.py