Metadata-Version: 1.0
Name: django-htauth
Version: 0.1
Summary: htpasswd authentication backend for django
Home-page: UNKNOWN
Author: Ethan Jucovy
Author-email: ethan@boldprogressives.org
License: BSD
Platform: UNKNOWN
Classifier: Development Status :: 4 - Beta
Classifier: Framework :: Django
Classifier: License :: OSI Approved :: BSD License
